{
  "__inputs": [
    {
      "name": "DS_SM_METRICS",
      "label": "Synthetic Monitoring Metrics",
      "description": "",
      "type": "datasource",
      "pluginId": "prometheus",
      "pluginName": "Prometheus"
    },
    {
      "name": "DS_SM_LOGS",
      "label": "Synthetic Monitoring Logs",
      "description": "",
      "type": "datasource",
      "pluginId": "loki",
      "pluginName": "Loki"
    }
  ],
  "__requires": [
    {
      "type": "grafana",
      "id": "grafana",
      "name": "Grafana",
      "version": "7.0.3"
    },
    {
      "type": "panel",
      "id": "grafana-worldmap-panel",
      "name": "Worldmap Panel",
      "version": "0.2.1"
    },
    {
      "type": "panel",
      "id": "graph",
      "name": "Graph",
      "version": ""
    },
    {
      "type": "panel",
      "id": "logs",
      "name": "Logs",
      "version": ""
    },
    {
      "type": "datasource",
      "id": "loki",
      "name": "Loki",
      "version": "1.0.0"
    },
    {
      "type": "datasource",
      "id": "prometheus",
      "name": "Prometheus",
      "version": "1.0.0"
    },
    {
      "type": "panel",
      "id": "stat",
      "name": "Stat",
      "version": ""
    }
  ],
  "annotations": {
    "list": [
      {
        "builtIn": 1,
        "datasource": "-- Grafana --",
        "enable": true,
        "hide": true,
        "iconColor": "rgba(0, 211, 255, 1)",
        "name": "Annotations & Alerts",
        "type": "dashboard"
      }
    ]
  },
  "editable": false,
  "gnetId": null,
  "graphTooltip": 0,
  "id": null,
  "iteration": 1596752049000,
  "links": [],
  "panels": [
    {
      "circleMaxSize": "10",
      "circleMinSize": "2",
      "colors": ["#37872D", "#FA6400", "#C4162A"],
      "datasource": "${DS_SM_METRICS}",
      "decimals": 2,
      "esGeoPoint": "geohash",
      "esLocationName": "probe",
      "esMetric": "Count",
      "fieldConfig": {
        "defaults": {
          "custom": {}
        },
        "overrides": []
      },
      "gridPos": {
        "h": 9,
        "w": 14,
        "x": 0,
        "y": 0
      },
      "hideEmpty": false,
      "hideZero": false,
      "id": 27,
      "initialZoom": 1,
      "locationData": "table",
      "mapCenter": "(0°, 0°)",
      "mapCenterLatitude": 0,
      "mapCenterLongitude": 0,
      "maxDataPoints": "",
      "mouseWheelZoom": false,
      "showLegend": false,
      "stickyLabels": false,
      "tableQueryOptions": {
        "geohashField": "geohash",
        "labelField": "probe",
        "latitudeField": "latitude",
        "longitudeField": "longitude",
        "metricField": "Value",
        "queryType": "geohash"
      },
      "targets": [
        {
          "expr": "100*(1 - (sum((rate(probe_all_success_sum{instance=\"$instance\", job=\"$job\"}[$__range]) OR rate(probe_success_sum{instance=\"$instance\", job=\"$job\"}[$__range])) * on (instance, job, probe, config_version) group_left(geohash) max(sm_check_info{check_name=\"dns\", instance=\"$instance\", job=\"$job\"}) by (instance, job, probe, config_version, geohash)) by (probe, geohash)/ sum((rate(probe_all_success_count{instance=\"$instance\", job=\"$job\"}[$__range]) OR rate(probe_success_count{instance=\"$instance\", job=\"$job\"}[$__range])) *  on (instance, job, probe, config_version) group_left(geohash) max(sm_check_info{check_name=\"dns\", instance=\"$instance\", job=\"$job\"}) by (instance, job, probe, config_version, geohash)) by (probe, geohash)))",
          "format": "table",
          "instant": true,
          "interval": "",
          "legendFormat": "",
          "refId": "A"
        }
      ],
      "thresholds": "0.5,1",
      "timeFrom": null,
      "timeShift": null,
      "title": "Downtime",
      "type": "grafana-worldmap-panel",
      "unitPlural": "%",
      "unitSingle": "",
      "unitSingular": "%",
      "valueName": "current"
    },
    {
      "cacheTimeout": null,
      "datasource": "${DS_SM_METRICS}",
      "fieldConfig": {
        "defaults": {
          "custom": {},
          "decimals": 2,
          "mappings": [
            {
              "id": 0,
              "op": "=",
              "text": "N/A",
              "type": 1,
              "value": "null"
            }
          ],
          "nullValueMode": "connected",
          "thresholds": {
            "mode": "absolute",
            "steps": [
              {
                "color": "red",
                "value": null
              },
              {
                "color": "#EAB839",
                "value": 0.99
              },
              {
                "color": "green",
                "value": 0.995
              }
            ]
          },
          "unit": "percentunit"
        },
        "overrides": []
      },
      "gridPos": {
        "h": 2,
        "w": 2,
        "x": 14,
        "y": 0
      },
      "id": 25,
      "links": [],
      "options": {
        "colorMode": "value",
        "fieldOptions": {
          "calcs": ["lastNotNull"]
        },
        "graphMode": "none",
        "justifyMode": "auto",
        "orientation": "horizontal",
        "reduceOptions": {
          "calcs": ["mean"],
          "fields": "",
          "values": false
        }
      },
      "pluginVersion": "7.0.3",
      "targets": [
        {
          "expr": "sum((rate(probe_all_success_sum{probe=~\"$probe\", instance=\"$instance\", job=\"$job\"}[$__range]) OR rate(probe_success_sum{probe=~\"$probe\", instance=\"$instance\", job=\"$job\"}[$__range]))) / sum((rate(probe_all_success_count{probe=~\"$probe\", instance=\"$instance\", job=\"$job\"}[$__range]) OR rate(probe_success_count{probe=~\"$probe\", instance=\"$instance\", job=\"$job\"}[$__range])))",
          "hide": false,
          "instant": false,
          "interval": "",
          "legendFormat": "",
          "refId": "B"
        }
      ],
      "timeFrom": null,
      "timeShift": null,
      "title": "Uptime",
      "type": "stat"
    },
    {
      "cacheTimeout": null,
      "datasource": "${DS_SM_METRICS}",
      "fieldConfig": {
        "defaults": {
          "custom": {},
          "decimals": 2,
          "mappings": [],
          "nullValueMode": "connected",
          "thresholds": {
            "mode": "absolute",
            "steps": [
              {
                "color": "green",
                "value": null
              },
              {
                "color": "yellow",
                "value": 1
              },
              {
                "color": "red",
                "value": 2
              }
            ]
          },
          "unit": "s"
        },
        "overrides": []
      },
      "gridPos": {
        "h": 2,
        "w": 3,
        "x": 16,
        "y": 0
      },
      "id": 30,
      "links": [],
      "options": {
        "colorMode": "value",
        "fieldOptions": {
          "calcs": ["lastNotNull"]
        },
        "graphMode": "none",
        "justifyMode": "auto",
        "orientation": "horizontal",
        "reduceOptions": {
          "calcs": ["last"],
          "fields": "",
          "values": false
        }
      },
      "pluginVersion": "7.0.3",
      "targets": [
        {
          "expr": "sum((rate(probe_dns_all_duration_seconds_sum{probe=~\"$probe\", instance=\"$instance\", job=\"$job\"}[$__range]) OR rate(probe_dns_duration_seconds_sum{probe=~\"$probe\", instance=\"$instance\", job=\"$job\"}[$__range]))) / sum((rate(probe_dns_all_duration_seconds_count{probe=~\"$probe\", instance=\"$instance\", job=\"$job\"}[$__range]) OR rate(probe_dns_duration_seconds_count{probe=~\"$probe\", instance=\"$instance\", job=\"$job\"}[$__range])))",
          "hide": false,
          "instant": true,
          "interval": "",
          "legendFormat": "",
          "refId": "B"
        }
      ],
      "timeFrom": null,
      "timeShift": null,
      "title": "Average Latency",
      "type": "stat"
    },
    {
      "cacheTimeout": null,
      "datasource": "${DS_SM_METRICS}",
      "fieldConfig": {
        "defaults": {
          "custom": {},
          "mappings": [
            {
              "id": 0,
              "op": "=",
              "text": "N/A",
              "type": 1,
              "value": "null"
            }
          ],
          "nullValueMode": "connected",
          "thresholds": {
            "mode": "absolute",
            "steps": [
              {
                "color": "green",
                "value": null
              }
            ]
          },
          "unit": "short"
        },
        "overrides": []
      },
      "gridPos": {
        "h": 2,
        "w": 3,
        "x": 19,
        "y": 0
      },
      "id": 32,
      "links": [],
      "options": {
        "colorMode": "value",
        "fieldOptions": {
          "calcs": ["lastNotNull"]
        },
        "graphMode": "none",
        "justifyMode": "auto",
        "orientation": "horizontal",
        "reduceOptions": {
          "calcs": ["mean"],
          "fields": "",
          "values": false
        }
      },
      "pluginVersion": "7.0.3",
      "targets": [
        {
          "expr": "avg(probe_dns_answer_rrs{probe=~\"$probe\",instance=\"$instance\", job=\"$job\"})",
          "hide": false,
          "instant": true,
          "interval": "",
          "legendFormat": "",
          "refId": "B"
        }
      ],
      "timeFrom": null,
      "timeShift": null,
      "title": "Answer Records",
      "type": "stat"
    },
    {
      "cacheTimeout": null,
      "datasource": "${DS_SM_METRICS}",
      "fieldConfig": {
        "defaults": {
          "custom": {
            "align": null
          },
          "decimals": 0,
          "mappings": [
            {
              "id": 0,
              "op": "=",
              "text": "N/A",
              "type": 1,
              "value": "null"
            }
          ],
          "nullValueMode": "connected",
          "thresholds": {
            "mode": "absolute",
            "steps": [
              {
                "color": "green",
                "value": null
              }
            ]
          },
          "unit": "ms"
        },
        "overrides": []
      },
      "gridPos": {
        "h": 2,
        "w": 2,
        "x": 22,
        "y": 0
      },
      "id": 17,
      "links": [],
      "options": {
        "colorMode": "value",
        "fieldOptions": {
          "calcs": ["mean"]
        },
        "graphMode": "none",
        "justifyMode": "auto",
        "orientation": "horizontal",
        "reduceOptions": {
          "calcs": ["last"],
          "fields": "",
          "values": false
        }
      },
      "pluginVersion": "7.0.3",
      "targets": [
        {
          "expr": "sum(topk(1,sm_check_info{probe=~\"$probe\", instance=\"$instance\", check_name=\"dns\"})) by (frequency)",
          "format": "table",
          "instant": true,
          "interval": "",
          "legendFormat": "{{frequency}}",
          "refId": "A"
        }
      ],
      "timeFrom": null,
      "timeShift": null,
      "title": "Frequency",
      "transformations": [
        {
          "id": "organize",
          "options": {
            "excludeByName": {
              "Value": true
            },
            "indexByName": {},
            "renameByName": {}
          }
        }
      ],
      "type": "stat"
    },
    {
      "aliasColors": {},
      "bars": false,
      "dashLength": 10,
      "dashes": false,
      "datasource": "${DS_SM_METRICS}",
      "description": "",
      "fieldConfig": {
        "defaults": {
          "custom": {}
        },
        "overrides": []
      },
      "fill": 10,
      "fillGradient": 0,
      "gridPos": {
        "h": 7,
        "w": 10,
        "x": 14,
        "y": 2
      },
      "hiddenSeries": false,
      "id": 8,
      "interval": "5m",
      "legend": {
        "avg": false,
        "current": false,
        "max": false,
        "min": false,
        "show": false,
        "total": false,
        "values": false
      },
      "lines": true,
      "linewidth": 0,
      "nullPointMode": "null",
      "options": {
        "dataLinks": []
      },
      "percentage": false,
      "pointradius": 2,
      "points": false,
      "renderer": "flot",
      "seriesOverrides": [],
      "spaceLength": 10,
      "stack": false,
      "steppedLine": true,
      "targets": [
        {
          "expr": "100*(1-(sum((rate(probe_all_success_sum{probe=~\"$probe\", instance=\"$instance\", job=\"$job\"}[$__interval]) OR rate(probe_success_sum{probe=~\"$probe\", instance=\"$instance\", job=\"$job\"}[$__interval]))) / sum((rate(probe_all_success_count{probe=~\"$probe\", instance=\"$instance\", job=\"$job\"}[$__interval]) OR rate(probe_success_count{probe=~\"$probe\", instance=\"$instance\", job=\"$job\"}[$__interval])))))",
          "hide": false,
          "interval": "",
          "legendFormat": "errors",
          "refId": "A"
        }
      ],
      "thresholds": [],
      "timeFrom": null,
      "timeRegions": [],
      "timeShift": null,
      "title": "Error Rate : $probe ⮕ $job / $instance",
      "tooltip": {
        "shared": true,
        "sort": 0,
        "value_type": "individual"
      },
      "type": "graph",
      "xaxis": {
        "buckets": null,
        "mode": "time",
        "name": null,
        "show": true,
        "values": []
      },
      "yaxes": [
        {
          "decimals": null,
          "format": "percent",
          "label": "",
          "logBase": 1,
          "max": "100",
          "min": "0",
          "show": true
        },
        {
          "format": "short",
          "label": null,
          "logBase": 1,
          "max": null,
          "min": null,
          "show": true
        }
      ],
      "yaxis": {
        "align": false,
        "alignLevel": null
      }
    },
    {
      "aliasColors": {},
      "bars": false,
      "dashLength": 10,
      "dashes": false,
      "datasource": "${DS_SM_METRICS}",
      "fieldConfig": {
        "defaults": {
          "custom": {}
        },
        "overrides": []
      },
      "fill": 10,
      "fillGradient": 0,
      "gridPos": {
        "h": 7,
        "w": 12,
        "x": 0,
        "y": 9
      },
      "hiddenSeries": false,
      "id": 29,
      "legend": {
        "alignAsTable": true,
        "avg": true,
        "current": true,
        "max": false,
        "min": false,
        "rightSide": true,
        "show": true,
        "sort": "current",
        "sortDesc": true,
        "total": false,
        "values": true
      },
      "lines": false,
      "linewidth": 0,
      "nullPointMode": "null",
      "options": {
        "dataLinks": []
      },
      "percentage": false,
      "pointradius": 1,
      "points": true,
      "renderer": "flot",
      "repeatDirection": null,
      "seriesOverrides": [
        {
          "alias": "transfer",
          "zindex": 3
        },
        {
          "alias": "processing",
          "zindex": 2
        },
        {
          "alias": "tls",
          "zindex": 1
        },
        {
          "alias": "connect",
          "zindex": 0
        },
        {
          "alias": "resolve",
          "zindex": -1
        }
      ],
      "spaceLength": 10,
      "stack": false,
      "steppedLine": false,
      "targets": [
        {
          "expr": "avg(probe_dns_duration_seconds{probe=~\"$probe\", instance=\"$instance\", job=\"$job\"}) by (probe)",
          "instant": false,
          "interval": "",
          "intervalFactor": 1,
          "legendFormat": "{{probe}}",
          "refId": "A"
        }
      ],
      "thresholds": [],
      "timeFrom": null,
      "timeRegions": [],
      "timeShift": null,
      "title": "Response Latency by Probe",
      "tooltip": {
        "shared": true,
        "sort": 0,
        "value_type": "individual"
      },
      "transformations": [],
      "type": "graph",
      "xaxis": {
        "buckets": null,
        "mode": "time",
        "name": null,
        "show": true,
        "values": []
      },
      "yaxes": [
        {
          "decimals": null,
          "format": "s",
          "label": null,
          "logBase": 1,
          "max": null,
          "min": null,
          "show": true
        },
        {
          "decimals": null,
          "format": "short",
          "label": null,
          "logBase": 1,
          "max": null,
          "min": null,
          "show": true
        }
      ],
      "yaxis": {
        "align": false,
        "alignLevel": null
      }
    },
    {
      "aliasColors": {},
      "bars": false,
      "dashLength": 10,
      "dashes": false,
      "datasource": "${DS_SM_METRICS}",
      "decimals": 0,
      "fieldConfig": {
        "defaults": {
          "custom": {}
        },
        "overrides": []
      },
      "fill": 0,
      "fillGradient": 0,
      "gridPos": {
        "h": 7,
        "w": 12,
        "x": 12,
        "y": 9
      },
      "hiddenSeries": false,
      "id": 12,
      "legend": {
        "alignAsTable": true,
        "avg": true,
        "current": true,
        "max": false,
        "min": false,
        "rightSide": true,
        "show": true,
        "total": false,
        "values": true
      },
      "lines": true,
      "linewidth": 2,
      "maxDataPoints": "100",
      "nullPointMode": "null",
      "options": {
        "dataLinks": []
      },
      "percentage": false,
      "pointradius": 2,
      "points": false,
      "renderer": "flot",
      "repeatDirection": null,
      "seriesOverrides": [
        {
          "alias": "transfer",
          "zindex": 3
        },
        {
          "alias": "processing",
          "zindex": 2
        },
        {
          "alias": "tls",
          "zindex": 1
        },
        {
          "alias": "connect",
          "zindex": 0
        },
        {
          "alias": "resolve",
          "zindex": -1
        }
      ],
      "spaceLength": 10,
      "stack": false,
      "steppedLine": false,
      "targets": [
        {
          "expr": "avg(probe_dns_answer_rrs{probe=~\"$probe\", instance=\"$instance\", job=\"$job\"})",
          "instant": false,
          "interval": "",
          "intervalFactor": 1,
          "legendFormat": "Answer Records",
          "refId": "A"
        },
        {
          "expr": "avg(probe_dns_authority_rrs{probe=~\"$probe\", instance=\"$instance\", job=\"$job\"})",
          "instant": false,
          "interval": "",
          "intervalFactor": 1,
          "legendFormat": "Authority Records",
          "refId": "B"
        },
        {
          "expr": "avg(probe_dns_additional_rrs{probe=~\"$probe\", instance=\"$instance\", job=\"$job\"})",
          "instant": false,
          "interval": "",
          "intervalFactor": 1,
          "legendFormat": "Additional Records",
          "refId": "C"
        }
      ],
      "thresholds": [],
      "timeFrom": null,
      "timeRegions": [],
      "timeShift": null,
      "title": "Resource Records",
      "tooltip": {
        "shared": true,
        "sort": 0,
        "value_type": "individual"
      },
      "transformations": [],
      "type": "graph",
      "xaxis": {
        "buckets": null,
        "mode": "time",
        "name": null,
        "show": true,
        "values": []
      },
      "yaxes": [
        {
          "decimals": 0,
          "format": "none",
          "label": null,
          "logBase": 1,
          "max": null,
          "min": null,
          "show": true
        },
        {
          "decimals": null,
          "format": "short",
          "label": null,
          "logBase": 1,
          "max": null,
          "min": null,
          "show": true
        }
      ],
      "yaxis": {
        "align": false,
        "alignLevel": null
      }
    },
    {
      "datasource": "${DS_SM_LOGS}",
      "fieldConfig": {
        "defaults": {
          "custom": {}
        },
        "overrides": []
      },
      "gridPos": {
        "h": 13,
        "w": 24,
        "x": 0,
        "y": 16
      },
      "id": 15,
      "options": {
        "showLabels": false,
        "showTime": true,
        "sortOrder": "Descending",
        "wrapLogMessage": true
      },
      "targets": [
        {
          "expr": "{probe=~\"$probe\",instance=\"$instance\", job=\"$job\", probe_success=\"0\"}",
          "refId": "A"
        }
      ],
      "timeFrom": null,
      "timeShift": null,
      "title": "Error logs for $probe: $instance",
      "type": "logs"
    }
  ],
  "refresh": "1m",
  "schemaVersion": 25,
  "style": "dark",
  "tags": ["synthetic-monitoring"],
  "templating": {
    "list": [
      {
        "allValue": ".*",
        "current": {},
        "datasource": "${DS_SM_METRICS}",
        "definition": "label_values(sm_check_info{check_name=\"dns\"},probe)",
        "hide": 0,
        "includeAll": true,
        "label": null,
        "multi": false,
        "name": "probe",
        "options": [],
        "query": "label_values(sm_check_info{check_name=\"dns\"},probe)",
        "refresh": 1,
        "regex": "",
        "skipUrlSync": false,
        "sort": 5,
        "tagValuesQuery": "",
        "tags": [],
        "tagsQuery": "",
        "type": "query",
        "useTags": false
      },
      {
        "allValue": null,
        "current": {},
        "datasource": "${DS_SM_METRICS}",
        "definition": "label_values(sm_check_info{check_name=\"dns\", probe=~\"$probe\"},job)",
        "hide": 0,
        "includeAll": false,
        "label": null,
        "multi": false,
        "name": "job",
        "options": [],
        "query": "label_values(sm_check_info{check_name=\"dns\", probe=~\"$probe\"},job)",
        "refresh": 1,
        "regex": "",
        "skipUrlSync": false,
        "sort": 1,
        "tagValuesQuery": "",
        "tags": [],
        "tagsQuery": "",
        "type": "query",
        "useTags": false
      },
      {
        "allValue": null,
        "current": {},
        "datasource": "${DS_SM_METRICS}",
        "definition": "label_values(sm_check_info{check_name=\"dns\", job=\"$job\", probe=~\"$probe\"},instance)",
        "hide": 0,
        "includeAll": false,
        "label": null,
        "multi": false,
        "name": "instance",
        "options": [],
        "query": "label_values(sm_check_info{check_name=\"dns\", job=\"$job\", probe=~\"$probe\"},instance)",
        "refresh": 1,
        "regex": "",
        "skipUrlSync": false,
        "sort": 5,
        "tagValuesQuery": "",
        "tags": [],
        "tagsQuery": "",
        "type": "query",
        "useTags": false
      }
    ]
  },
  "time": {
    "from": "now-3h",
    "to": "now"
  },
  "timepicker": {
    "refresh_intervals": ["10s", "30s", "1m", "5m", "15m", "30m", "1h", "2h", "1d"]
  },
  "timezone": "",
  "title": "Synthetic Monitoring - DNS",
  "uid": "lgL6odgGz",
  "version": 15
}
